[
  {
    "name": "Salami Sub",
    "description": "Belegt mit Salat, Gurken, Tomaten & Käse überbacken",
    "category": "Subs",
    "price": 9.0,
    "image": "/img/salami_sub.jpeg"
  },
  {
    "name": "Schinken Sub",
    "description": "Belegt mit Salat, Gurken, Tomaten & Käse überbacken",
    "category": "Subs",
    "price": 9.0,
    "image": "/img/schinken_sub.jpeg"
  },
  {
    "name": "Hawaii Sub",
    "description": "Belegt mit Schinken, Ananas, Salat, Gurken, Tomaten & Käse überbacken",
    "category": "Subs",
    "price": 9.5,
    "image": "/img/hawaii_sub.jpeg"
  },
  {
    "name": "Orient Sub",
    "description": "Belegt mit Sucuk, Spiegelei, Salat, Gurken, Tomaten & Käse überbacken",
    "category": "Subs",
    "price": 10.0,
    "image": "/img/orient_sub.jpeg"
  },
  {
    "name": "Thunfisch Sub",
    "description": "Belegt mit Salat, Gurken, Tomaten, Zwiebeln & Käse überbacken",
    "category": "Subs",
    "price": 9.5,
    "image": "/img/thunfisch_sub.jpeg"
  },
  {
    "name": "Chicken Sub",
    "description": "Belegt mit angebratenen Hähnchenstreifen, Salat, Gurken, Tomaten, Zwiebeln & Käse überbacken",
    "category": "Subs",
    "price": 11.0,
    "image": "/img/chicken_sub.jpeg"
  },
  {
    "name": "Hot Chili Sub",
    "description": "Belegt mit Salami, Schinken, Jalapeños, Salat, Gurken, Tomaten, Paprika & Käse überbacken",
    "category": "Subs",
    "price": 10.0,
    "image": "/img/hot_chili_sub.jpeg"
  },
  {
    "name": "Veggi Sub",
    "description": "Belegt mit Brokkoli, Paprika, Hirtenkäse, Salat, Gurken, Tomaten & Käse überbacken",
    "category": "Subs",
    "price": 9.0,
    "image": "/img/veggi_sub.jpeg"
  }
]
